CHANGES.rst
LICENSE.txt
pypfop/__init__.py
pypfop/builder.py
pypfop/conversion.py
pypfop/document_generator.py
pypfop/exceptions.py
pypfop/helpers.py
pypfop/skeletons/mako/A4-landscape.fo.mako
pypfop/skeletons/mako/A4-portrait.fo.mako
pypfop/skeletons/mako/base.fo.mako
pypfop/skeletons/mako/letter-landscape.fo.mako
pypfop/skeletons/mako/letter-portrait.fo.mako
pypfop/templates/__init__.py
pypfop/templates/mako.py
pypfop-1.0a1.dist-info/LICENSE.txt
pypfop-1.0a1.dist-info/WHEEL
pypfop-1.0a1.dist-info/METADATA
pypfop-1.0a1.dist-info/RECORD
