Metadata-Version: 2.1
Name: pypfop
Version: 1.0a1
Summary: Document preprocessor for Apache FOP
Home-page: https://github.com/cyraxjoe/pypfop
License: Apache-2.0
Author: Joel Rivera
Author-email: rivera@joel.mx
Requires-Python: >=3.6,<4.0
Classifier: Development Status :: 3 - Alpha
Classifier: Intended Audience :: Developers
Classifier: License :: OSI Approved :: Apache Software License
Classifier: Operating System :: OS Independent
Classifier: Programming Language :: Python :: 3
Classifier: Programming Language :: Python :: 3.6
Classifier: Programming Language :: Python :: 3.7
Classifier: Programming Language :: Python :: 3.8
Classifier: Programming Language :: Python :: 3.9
Classifier: Topic :: Office/Business
Classifier: Topic :: Software Development :: Libraries
Classifier: Topic :: Text Processing :: Filters
Requires-Dist: Mako (>=1.1.4,<2.0.0)
Requires-Dist: cssselect (>=1.1.0,<2.0.0)
Requires-Dist: cssutils (>=1.0.2,<2.0.0)
Requires-Dist: lxml (>=4.6.2,<5.0.0)
